[{"id":1,"kdProfile":"0","noRegistrasi":"1511000009","noCM":"L11111111","tglPeriksa":"11/18/2015 11:02:00 am","kdDokter":"A7a00","kdRuangan":"Ca1","kdKasusPenyakit":"2","diagramOdonto":null,"keterangan":"Keterangan","statusEnabled":"1"},{"id":2,"kdProfile":"0","noRegistrasi":"1511000009","noCM":"L11111111","tglPeriksa":"1/7/2016 3:36:00 pm","kdDokter":"A7a00","kdRuangan":"Ca1","kdKasusPenyakit":"2","diagramOdonto":null,"keterangan":"Keterangan","statusEnabled":"1"},{"id":3,"kdProfile":"0","noRegistrasi":"1511000009","noCM":"L11111111","tglPeriksa":"1/7/2016 4:03:00 pm","kdDokter":"A7a00","kdRuangan":"Ca1","kdKasusPenyakit":"2","diagramOdonto":null,"keterangan":"Keterangan","statusEnabled":"1"},{"id":4,"kdProfile":"0","noRegistrasi":"1511000009","noCM":"L11111111","tglPeriksa":"1/7/2016 5:09:00 pm","kdDokter":"A7a00","kdRuangan":"Ca1","kdKasusPenyakit":"2","diagramOdonto":null,"keterangan":"Keterangan","statusEnabled":"1"},{"id":5,"kdProfile":"0","noRegistrasi":"1511000009","noCM":"L11111111","tglPeriksa":"1/7/2016 5:16:00 pm","kdDokter":"A7a00","kdRuangan":"Ca1","kdKasusPenyakit":"2","diagramOdonto":null,"keterangan":"Keterangan","statusEnabled":"1"},{"id":6,"kdProfile":"0","noRegistrasi":"1511000009","noCM":"L11111111","tglPeriksa":"1/7/2016 5:20:00 pm","kdDokter":"A7a00","kdRuangan":"Ca1","kdKasusPenyakit":"2","diagramOdonto":null,"keterangan":"Keterangan","statusEnabled":"1"},{"id":7,"kdProfile":"0","noRegistrasi":"1511000009","noCM":"L11111111","tglPeriksa":"1/7/2016 5:24:00 pm","kdDokter":"A7a00","kdRuangan":"Ca1","kdKasusPenyakit":"2","diagramOdonto":null,"keterangan":"Keterangan","statusEnabled":"1"}]