[{"id":1,"kdProfile":"0","kdHari":"1","namaHari":"Minggu","reportDisplay":"Minggu","noUrutHariKe":"1","qHari":"1","kodeExternal":null,"namaExternal":null,"statusEnabled":"1"},{"id":2,"kdProfile":"0","kdHari":"2","namaHari":"Senin","reportDisplay":"Senin","noUrutHariKe":"2","qHari":"2","kodeExternal":null,"namaExternal":null,"statusEnabled":"1"},{"id":3,"kdProfile":"0","kdHari":"3","namaHari":"Selasa","reportDisplay":"Selasa","noUrutHariKe":"3","qHari":"3","kodeExternal":null,"namaExternal":null,"statusEnabled":"1"},{"id":4,"kdProfile":"0","kdHari":"4","namaHari":"Rabu","reportDisplay":"Rabu","noUrutHariKe":"4","qHari":"4","kodeExternal":null,"namaExternal":null,"statusEnabled":"1"},{"id":5,"kdProfile":"0","kdHari":"5","namaHari":"Kamis","reportDisplay":"Kamis","noUrutHariKe":"5","qHari":"5","kodeExternal":null,"namaExternal":null,"statusEnabled":"1"},{"id":6,"kdProfile":"0","kdHari":"6","namaHari":"Jumat","reportDisplay":"Jumat","noUrutHariKe":"6","qHari":"6","kodeExternal":null,"namaExternal":null,"statusEnabled":"1"},{"id":7,"kdProfile":"0","kdHari":"7","namaHari":"Sabtu","reportDisplay":"Sabtu","noUrutHariKe":"7","qHari":"7","kodeExternal":null,"namaExternal":null,"statusEnabled":"1"}]