[{"id":1,"kdProfile":"0","kdJenisPeriksa":"1","jenisPeriksa":"Hematologi","reportDisplay":"Hematologi","noUrut":"0","kdDepartemen":"H","kdJenisPeriksaHead":null,"kdBahanSample":"C","qJenisPeriksa":"1","kodeExternal":null,"namaExternal":null,"statusEnabled":"1"},{"id":2,"kdProfile":"0","kdJenisPeriksa":"2","jenisPeriksa":"Kimia klinik","reportDisplay":"Kimia klinik","noUrut":"0","kdDepartemen":"H","kdJenisPeriksaHead":null,"kdBahanSample":"C","qJenisPeriksa":"2","kodeExternal":null,"namaExternal":null,"statusEnabled":"1"},{"id":3,"kdProfile":"0","kdJenisPeriksa":"3","jenisPeriksa":"Serologi","reportDisplay":"Serologi","noUrut":"0","kdDepartemen":"H","kdJenisPeriksaHead":null,"kdBahanSample":"C","qJenisPeriksa":"3","kodeExternal":null,"namaExternal":null,"statusEnabled":"1"},{"id":4,"kdProfile":"0","kdJenisPeriksa":"4","jenisPeriksa":"Urine","reportDisplay":"Urine","noUrut":"0","kdDepartemen":"H","kdJenisPeriksaHead":null,"kdBahanSample":"B","qJenisPeriksa":"4","kodeExternal":null,"namaExternal":null,"statusEnabled":"1"},{"id":5,"kdProfile":"0","kdJenisPeriksa":"5","jenisPeriksa":"Mikrobiologi","reportDisplay":"Mikrobiologi","noUrut":"0","kdDepartemen":"H","kdJenisPeriksaHead":null,"kdBahanSample":"E","qJenisPeriksa":"5","kodeExternal":null,"namaExternal":null,"statusEnabled":"1"},{"id":6,"kdProfile":"0","kdJenisPeriksa":"6","jenisPeriksa":"Faeces","reportDisplay":"Faeces","noUrut":"0","kdDepartemen":"H","kdJenisPeriksaHead":null,"kdBahanSample":"F","qJenisPeriksa":"6","kodeExternal":null,"namaExternal":null,"statusEnabled":"1"},{"id":7,"kdProfile":"0","kdJenisPeriksa":"7","jenisPeriksa":"Bakteriologi","reportDisplay":"Bakteriologi","noUrut":"0","kdDepartemen":"H","kdJenisPeriksaHead":null,"kdBahanSample":"E","qJenisPeriksa":"7","kodeExternal":null,"namaExternal":null,"statusEnabled":"1"},{"id":8,"kdProfile":"0","kdJenisPeriksa":"8","jenisPeriksa":"Mikrobiologi","reportDisplay":"Mikrobiologi","noUrut":"0","kdDepartemen":"H","kdJenisPeriksaHead":null,"kdBahanSample":"G","qJenisPeriksa":"8","kodeExternal":null,"namaExternal":null,"statusEnabled":"1"},{"id":9,"kdProfile":"0","kdJenisPeriksa":"9","jenisPeriksa":"Fnab","reportDisplay":"Fnab","noUrut":"0","kdDepartemen":"H","kdJenisPeriksaHead":null,"kdBahanSample":"C","qJenisPeriksa":"9","kodeExternal":null,"namaExternal":null,"statusEnabled":"1"},{"id":10,"kdProfile":"0","kdJenisPeriksa":"10","jenisPeriksa":"Kimia darah","reportDisplay":"Kimia darah","noUrut":"0","kdDepartemen":"H","kdJenisPeriksaHead":null,"kdBahanSample":"C","qJenisPeriksa":"10","kodeExternal":null,"namaExternal":null,"statusEnabled":"1"},{"id":11,"kdProfile":"0","kdJenisPeriksa":"11","jenisPeriksa":"Thorax","reportDisplay":"Thorax","noUrut":"0","kdDepartemen":"I","kdJenisPeriksaHead":null,"kdBahanSample":"C","qJenisPeriksa":"11","kodeExternal":null,"namaExternal":null,"statusEnabled":"1"},{"id":12,"kdProfile":"0","kdJenisPeriksa":"12","jenisPeriksa":"Abdomen","reportDisplay":"Abdomen","noUrut":"0","kdDepartemen":"I","kdJenisPeriksaHead":null,"kdBahanSample":"C","qJenisPeriksa":"12","kodeExternal":null,"namaExternal":null,"statusEnabled":"1"},{"id":13,"kdProfile":"0","kdJenisPeriksa":"13","jenisPeriksa":"Abd. 3posisi","reportDisplay":"Abd. 3posisi","noUrut":"0","kdDepartemen":"I","kdJenisPeriksaHead":null,"kdBahanSample":"C","qJenisPeriksa":"13","kodeExternal":null,"namaExternal":null,"statusEnabled":"1"},{"id":14,"kdProfile":"0","kdJenisPeriksa":"14","jenisPeriksa":"Usg","reportDisplay":"Usg","noUrut":"0","kdDepartemen":"I","kdJenisPeriksaHead":null,"kdBahanSample":"C","qJenisPeriksa":"14","kodeExternal":null,"namaExternal":null,"statusEnabled":"1"},{"id":15,"kdProfile":"0","kdJenisPeriksa":"15","jenisPeriksa":"Mandibula","reportDisplay":"Mandibula","noUrut":"0","kdDepartemen":"I","kdJenisPeriksaHead":null,"kdBahanSample":"C","qJenisPeriksa":"15","kodeExternal":null,"namaExternal":null,"statusEnabled":"1"},{"id":16,"kdProfile":"0","kdJenisPeriksa":"16","jenisPeriksa":"Mikrobiologi","reportDisplay":"Mikrobiologi","noUrut":"0","kdDepartemen":"H","kdJenisPeriksaHead":null,"kdBahanSample":"I","qJenisPeriksa":"16","kodeExternal":null,"namaExternal":null,"statusEnabled":"1"},{"id":17,"kdProfile":"0","kdJenisPeriksa":"17","jenisPeriksa":"Imunologi","reportDisplay":"Imunologi","noUrut":"0","kdDepartemen":"H","kdJenisPeriksaHead":null,"kdBahanSample":"C","qJenisPeriksa":"17","kodeExternal":null,"namaExternal":null,"statusEnabled":"1"},{"id":18,"kdProfile":"0","kdJenisPeriksa":"18","jenisPeriksa":"Narkotika","reportDisplay":"Narkotika","noUrut":"0","kdDepartemen":"H","kdJenisPeriksaHead":null,"kdBahanSample":"B","qJenisPeriksa":"18","kodeExternal":null,"namaExternal":null,"statusEnabled":"1"},{"id":19,"kdProfile":"0","kdJenisPeriksa":"19","jenisPeriksa":"Psikotropika","reportDisplay":"Psikotropika","noUrut":"0","kdDepartemen":"H","kdJenisPeriksaHead":null,"kdBahanSample":"B","qJenisPeriksa":"19","kodeExternal":null,"namaExternal":null,"statusEnabled":"1"},{"id":20,"kdProfile":"0","kdJenisPeriksa":"20","jenisPeriksa":"Pestisida","reportDisplay":"Pestisida","noUrut":"0","kdDepartemen":"H","kdJenisPeriksaHead":null,"kdBahanSample":"D","qJenisPeriksa":"20","kodeExternal":null,"namaExternal":null,"statusEnabled":"1"},{"id":21,"kdProfile":"0","kdJenisPeriksa":"21","jenisPeriksa":"Mikrobiologi","reportDisplay":"Mikrobiologi","noUrut":"0","kdDepartemen":"H","kdJenisPeriksaHead":null,"kdBahanSample":"H","qJenisPeriksa":"21","kodeExternal":null,"namaExternal":null,"statusEnabled":"1"},{"id":22,"kdProfile":"0","kdJenisPeriksa":"22","jenisPeriksa":"Toksikologi","reportDisplay":"Toksikologi","noUrut":"0","kdDepartemen":"H","kdJenisPeriksaHead":null,"kdBahanSample":"E","qJenisPeriksa":"22","kodeExternal":null,"namaExternal":null,"statusEnabled":"1"},{"id":23,"kdProfile":"0","kdJenisPeriksa":"23","jenisPeriksa":"Hematologi","reportDisplay":"Hematologi","noUrut":"0","kdDepartemen":"H","kdJenisPeriksaHead":null,"kdBahanSample":"C","qJenisPeriksa":"23","kodeExternal":null,"namaExternal":null,"statusEnabled":"0"},{"id":24,"kdProfile":"0","kdJenisPeriksa":"24","jenisPeriksa":"Darah lengkap","reportDisplay":"Darah lengkap","noUrut":"0","kdDepartemen":"H","kdJenisPeriksaHead":"1","kdBahanSample":"C","qJenisPeriksa":"24","kodeExternal":"01","namaExternal":"Darah lengkap","statusEnabled":"1"}]