[{"id":1,"kdProfile":"0","kdRange":"0","namaRange":"Nilai normal","rangeMin":"0","rangeMax":"999","kdJenisRange":"1","qRange":"1","kodeExternal":"01","namaExternal":"Nilai normal","statusEnabled":"1"},{"id":2,"kdProfile":"0","kdRange":"1","namaRange":"Nilai normal","rangeMin":"15","rangeMax":"30","kdJenisRange":"1","qRange":"5","kodeExternal":"02","namaExternal":"Nilai normal","statusEnabled":"1"},{"id":3,"kdProfile":"0","kdRange":"2","namaRange":"Nilai normal","rangeMin":"1","rangeMax":"2","kdJenisRange":"1","qRange":"6","kodeExternal":"03","namaExternal":"Nilai normal","statusEnabled":"1"},{"id":4,"kdProfile":"0","kdRange":"3","namaRange":"Nilai normal","rangeMin":"24","rangeMax":"170","kdJenisRange":"1","qRange":"7","kodeExternal":"04","namaExternal":"Nilai normal","statusEnabled":"1"},{"id":5,"kdProfile":"0","kdRange":"4","namaRange":"Nilai normal","rangeMin":"240","rangeMax":"480","kdJenisRange":"1","qRange":"8","kodeExternal":"05","namaExternal":"Nilai normal","statusEnabled":"1"},{"id":6,"kdProfile":"0","kdRange":"5","namaRange":"Waktu toleransi","rangeMin":"1","rangeMax":"2","kdJenisRange":"2","qRange":"9","kodeExternal":"06","namaExternal":"Waktu toleransi","statusEnabled":"1"}]