[{"id":1,"kdProfile":"0","kdKamar":"1","nomorBed":"1","isVirtual":"0","kdStatusBed":"1","statusEnabled":"1"},{"id":2,"kdProfile":"0","kdKamar":"5","nomorBed":"1","isVirtual":"0","kdStatusBed":"2","statusEnabled":"0"},{"id":3,"kdProfile":"0","kdKamar":"5","nomorBed":"2","isVirtual":"0","kdStatusBed":"2","statusEnabled":"0"},{"id":4,"kdProfile":"0","kdKamar":"5","nomorBed":"3","isVirtual":"0","kdStatusBed":"2","statusEnabled":"0"},{"id":5,"kdProfile":"0","kdKamar":"5","nomorBed":"4","isVirtual":"0","kdStatusBed":"2","statusEnabled":"0"},{"id":6,"kdProfile":"0","kdKamar":"6","nomorBed":"1","isVirtual":"0","kdStatusBed":"2","statusEnabled":"1"},{"id":7,"kdProfile":"0","kdKamar":"6","nomorBed":"2","isVirtual":"0","kdStatusBed":"2","statusEnabled":"1"},{"id":8,"kdProfile":"0","kdKamar":"6","nomorBed":"3","isVirtual":"0","kdStatusBed":"2","statusEnabled":"1"},{"id":9,"kdProfile":"0","kdKamar":"6","nomorBed":"4","isVirtual":"0","kdStatusBed":"2","statusEnabled":"1"},{"id":10,"kdProfile":"0","kdKamar":"6","nomorBed":"5","isVirtual":"0","kdStatusBed":"2","statusEnabled":"1"},{"id":11,"kdProfile":"0","kdKamar":"6","nomorBed":"6","isVirtual":"0","kdStatusBed":"2","statusEnabled":"1"},{"id":12,"kdProfile":"0","kdKamar":"7","nomorBed":"1","isVirtual":"0","kdStatusBed":"2","statusEnabled":"1"},{"id":13,"kdProfile":"0","kdKamar":"7","nomorBed":"2","isVirtual":"0","kdStatusBed":"1","statusEnabled":"1"},{"id":14,"kdProfile":"0","kdKamar":"7","nomorBed":"3","isVirtual":"0","kdStatusBed":"1","statusEnabled":"1"},{"id":15,"kdProfile":"0","kdKamar":"7","nomorBed":"4","isVirtual":"0","kdStatusBed":"1","statusEnabled":"1"},{"id":16,"kdProfile":"0","kdKamar":"7","nomorBed":"5","isVirtual":"0","kdStatusBed":"1","statusEnabled":"1"},{"id":17,"kdProfile":"0","kdKamar":"7","nomorBed":"6","isVirtual":"0","kdStatusBed":"1","statusEnabled":"1"},{"id":18,"kdProfile":"0","kdKamar":"7","nomorBed":"7","isVirtual":"0","kdStatusBed":"1","statusEnabled":"1"},{"id":19,"kdProfile":"0","kdKamar":"7","nomorBed":"8","isVirtual":"0","kdStatusBed":"1","statusEnabled":"1"},{"id":20,"kdProfile":"0","kdKamar":"7","nomorBed":"9","isVirtual":"0","kdStatusBed":"2","statusEnabled":"1"},{"id":21,"kdProfile":"0","kdKamar":"7","nomorBed":"10","isVirtual":"0","kdStatusBed":"2","statusEnabled":"1"},{"id":22,"kdProfile":"0","kdKamar":"7","nomorBed":"11","isVirtual":"0","kdStatusBed":"2","statusEnabled":"1"},{"id":23,"kdProfile":"0","kdKamar":"7","nomorBed":"12","isVirtual":"0","kdStatusBed":"1","statusEnabled":"1"},{"id":24,"kdProfile":"0","kdKamar":"7","nomorBed":"13","isVirtual":"0","kdStatusBed":"1","statusEnabled":"1"},{"id":25,"kdProfile":"0","kdKamar":"7","nomorBed":"14","isVirtual":"0","kdStatusBed":"2","statusEnabled":"1"},{"id":26,"kdProfile":"0","kdKamar":"7","nomorBed":"15","isVirtual":"0","kdStatusBed":"1","statusEnabled":"1"},{"id":27,"kdProfile":"0","kdKamar":"7","nomorBed":"16","isVirtual":"0","kdStatusBed":"1","statusEnabled":"1"},{"id":28,"kdProfile":"0","kdKamar":"7","nomorBed":"17","isVirtual":"0","kdStatusBed":"2","statusEnabled":"1"},{"id":29,"kdProfile":"0","kdKamar":"7","nomorBed":"18","isVirtual":"0","kdStatusBed":"1","statusEnabled":"1"},{"id":30,"kdProfile":"0","kdKamar":"7","nomorBed":"19","isVirtual":"0","kdStatusBed":"2","statusEnabled":"1"},{"id":31,"kdProfile":"0","kdKamar":"7","nomorBed":"20","isVirtual":"0","kdStatusBed":"2","statusEnabled":"1"},{"id":32,"kdProfile":"0","kdKamar":"8","nomorBed":"1","isVirtual":"0","kdStatusBed":"2","statusEnabled":"1"},{"id":33,"kdProfile":"0","kdKamar":"8","nomorBed":"2","isVirtual":"0","kdStatusBed":"2","statusEnabled":"1"},{"id":34,"kdProfile":"0","kdKamar":"8","nomorBed":"3","isVirtual":"0","kdStatusBed":"2","statusEnabled":"1"},{"id":35,"kdProfile":"0","kdKamar":"8","nomorBed":"4","isVirtual":"0","kdStatusBed":"2","statusEnabled":"1"},{"id":36,"kdProfile":"0","kdKamar":"8","nomorBed":"5","isVirtual":"0","kdStatusBed":"2","statusEnabled":"1"},{"id":37,"kdProfile":"0","kdKamar":"8","nomorBed":"6","isVirtual":"0","kdStatusBed":"2","statusEnabled":"1"},{"id":38,"kdProfile":"0","kdKamar":"9","nomorBed":"1","isVirtual":"0","kdStatusBed":"2","statusEnabled":"1"},{"id":39,"kdProfile":"0","kdKamar":"9","nomorBed":"2","isVirtual":"0","kdStatusBed":"2","statusEnabled":"1"},{"id":40,"kdProfile":"0","kdKamar":"9","nomorBed":"3","isVirtual":"0","kdStatusBed":"1","statusEnabled":"1"},{"id":41,"kdProfile":"0","kdKamar":"9","nomorBed":"4","isVirtual":"0","kdStatusBed":"2","statusEnabled":"1"},{"id":42,"kdProfile":"0","kdKamar":"9","nomorBed":"5","isVirtual":"0","kdStatusBed":"2","statusEnabled":"1"},{"id":43,"kdProfile":"0","kdKamar":"9","nomorBed":"6","isVirtual":"0","kdStatusBed":"2","statusEnabled":"1"},{"id":44,"kdProfile":"0","kdKamar":"9","nomorBed":"7","isVirtual":"0","kdStatusBed":"2","statusEnabled":"1"},{"id":45,"kdProfile":"0","kdKamar":"9","nomorBed":"8","isVirtual":"0","kdStatusBed":"2","statusEnabled":"1"},{"id":46,"kdProfile":"0","kdKamar":"9","nomorBed":"9","isVirtual":"0","kdStatusBed":"2","statusEnabled":"1"},{"id":47,"kdProfile":"0","kdKamar":"9","nomorBed":"10","isVirtual":"0","kdStatusBed":"2","statusEnabled":"1"},{"id":48,"kdProfile":"0","kdKamar":"9","nomorBed":"11","isVirtual":"0","kdStatusBed":"2","statusEnabled":"1"},{"id":49,"kdProfile":"0","kdKamar":"9","nomorBed":"12","isVirtual":"0","kdStatusBed":"2","statusEnabled":"1"},{"id":50,"kdProfile":"0","kdKamar":"9","nomorBed":"13","isVirtual":"0","kdStatusBed":"2","statusEnabled":"1"},{"id":51,"kdProfile":"0","kdKamar":"9","nomorBed":"14","isVirtual":"0","kdStatusBed":"2","statusEnabled":"1"},{"id":52,"kdProfile":"0","kdKamar":"9","nomorBed":"15","isVirtual":"0","kdStatusBed":"2","statusEnabled":"1"},{"id":53,"kdProfile":"0","kdKamar":"9","nomorBed":"16","isVirtual":"0","kdStatusBed":"2","statusEnabled":"1"},{"id":54,"kdProfile":"0","kdKamar":"9","nomorBed":"17","isVirtual":"0","kdStatusBed":"2","statusEnabled":"1"},{"id":55,"kdProfile":"0","kdKamar":"9","nomorBed":"18","isVirtual":"0","kdStatusBed":"2","statusEnabled":"1"},{"id":56,"kdProfile":"0","kdKamar":"9","nomorBed":"19","isVirtual":"0","kdStatusBed":"2","statusEnabled":"1"},{"id":57,"kdProfile":"0","kdKamar":"9","nomorBed":"20","isVirtual":"0","kdStatusBed":"2","statusEnabled":"1"},{"id":58,"kdProfile":"0","kdKamar":"10","nomorBed":"1","isVirtual":"0","kdStatusBed":"2","statusEnabled":"1"},{"id":59,"kdProfile":"0","kdKamar":"10","nomorBed":"2","isVirtual":"0","kdStatusBed":"2","statusEnabled":"1"},{"id":60,"kdProfile":"0","kdKamar":"10","nomorBed":"3","isVirtual":"0","kdStatusBed":"2","statusEnabled":"1"},{"id":61,"kdProfile":"0","kdKamar":"10","nomorBed":"4","isVirtual":"0","kdStatusBed":"2","statusEnabled":"1"},{"id":62,"kdProfile":"0","kdKamar":"10","nomorBed":"5","isVirtual":"0","kdStatusBed":"2","statusEnabled":"1"},{"id":63,"kdProfile":"0","kdKamar":"10","nomorBed":"6","isVirtual":"0","kdStatusBed":"2","statusEnabled":"1"},{"id":64,"kdProfile":"0","kdKamar":"10","nomorBed":"7","isVirtual":"0","kdStatusBed":"2","statusEnabled":"1"},{"id":65,"kdProfile":"0","kdKamar":"10","nomorBed":"8","isVirtual":"0","kdStatusBed":"2","statusEnabled":"1"},{"id":66,"kdProfile":"0","kdKamar":"10","nomorBed":"9","isVirtual":"0","kdStatusBed":"2","statusEnabled":"1"},{"id":67,"kdProfile":"0","kdKamar":"10","nomorBed":"10","isVirtual":"0","kdStatusBed":"2","statusEnabled":"1"},{"id":68,"kdProfile":"0","kdKamar":"11","nomorBed":"1","isVirtual":"0","kdStatusBed":"2","statusEnabled":"1"},{"id":69,"kdProfile":"0","kdKamar":"11","nomorBed":"2","isVirtual":"0","kdStatusBed":"2","statusEnabled":"1"},{"id":70,"kdProfile":"0","kdKamar":"11","nomorBed":"3","isVirtual":"0","kdStatusBed":"2","statusEnabled":"1"},{"id":71,"kdProfile":"0","kdKamar":"11","nomorBed":"4","isVirtual":"0","kdStatusBed":"2","statusEnabled":"1"},{"id":72,"kdProfile":"0","kdKamar":"11","nomorBed":"5","isVirtual":"0","kdStatusBed":"2","statusEnabled":"1"},{"id":73,"kdProfile":"0","kdKamar":"12","nomorBed":"1","isVirtual":"0","kdStatusBed":"2","statusEnabled":"1"},{"id":74,"kdProfile":"0","kdKamar":"12","nomorBed":"2","isVirtual":"0","kdStatusBed":"2","statusEnabled":"1"},{"id":75,"kdProfile":"0","kdKamar":"13","nomorBed":"1","isVirtual":"0","kdStatusBed":"2","statusEnabled":"1"},{"id":76,"kdProfile":"0","kdKamar":"13","nomorBed":"2","isVirtual":"0","kdStatusBed":"2","statusEnabled":"1"},{"id":77,"kdProfile":"0","kdKamar":"13","nomorBed":"3","isVirtual":"0","kdStatusBed":"2","statusEnabled":"1"},{"id":78,"kdProfile":"0","kdKamar":"13","nomorBed":"4","isVirtual":"0","kdStatusBed":"2","statusEnabled":"1"},{"id":79,"kdProfile":"0","kdKamar":"13","nomorBed":"5","isVirtual":"0","kdStatusBed":"2","statusEnabled":"1"},{"id":80,"kdProfile":"0","kdKamar":"13","nomorBed":"6","isVirtual":"0","kdStatusBed":"2","statusEnabled":"1"},{"id":81,"kdProfile":"0","kdKamar":"13","nomorBed":"7","isVirtual":"0","kdStatusBed":"2","statusEnabled":"1"},{"id":82,"kdProfile":"0","kdKamar":"13","nomorBed":"8","isVirtual":"0","kdStatusBed":"2","statusEnabled":"1"},{"id":83,"kdProfile":"0","kdKamar":"13","nomorBed":"9","isVirtual":"0","kdStatusBed":"2","statusEnabled":"1"},{"id":84,"kdProfile":"0","kdKamar":"13","nomorBed":"10","isVirtual":"0","kdStatusBed":"2","statusEnabled":"1"},{"id":85,"kdProfile":"0","kdKamar":"14","nomorBed":"1","isVirtual":"0","kdStatusBed":"2","statusEnabled":"1"},{"id":86,"kdProfile":"0","kdKamar":"14","nomorBed":"2","isVirtual":"0","kdStatusBed":"2","statusEnabled":"1"},{"id":87,"kdProfile":"0","kdKamar":"14","nomorBed":"3","isVirtual":"0","kdStatusBed":"2","statusEnabled":"1"},{"id":88,"kdProfile":"0","kdKamar":"14","nomorBed":"4","isVirtual":"0","kdStatusBed":"2","statusEnabled":"1"},{"id":89,"kdProfile":"0","kdKamar":"14","nomorBed":"5","isVirtual":"0","kdStatusBed":"2","statusEnabled":"1"},{"id":90,"kdProfile":"0","kdKamar":"15","nomorBed":"1","isVirtual":"0","kdStatusBed":"2","statusEnabled":"1"},{"id":91,"kdProfile":"0","kdKamar":"15","nomorBed":"2","isVirtual":"0","kdStatusBed":"2","statusEnabled":"1"},{"id":92,"kdProfile":"0","kdKamar":"16","nomorBed":"1","isVirtual":"0","kdStatusBed":"2","statusEnabled":"1"},{"id":93,"kdProfile":"0","kdKamar":"17","nomorBed":"1","isVirtual":"0","kdStatusBed":"2","statusEnabled":"1"},{"id":94,"kdProfile":"0","kdKamar":"18","nomorBed":"1","isVirtual":"0","kdStatusBed":"2","statusEnabled":"1"},{"id":95,"kdProfile":"0","kdKamar":"19","nomorBed":"1","isVirtual":"0","kdStatusBed":"2","statusEnabled":"1"},{"id":96,"kdProfile":"0","kdKamar":"20","nomorBed":"1","isVirtual":"0","kdStatusBed":"2","statusEnabled":"1"},{"id":97,"kdProfile":"0","kdKamar":"21","nomorBed":"1","isVirtual":"0","kdStatusBed":"2","statusEnabled":"1"},{"id":98,"kdProfile":"0","kdKamar":"22","nomorBed":"1","isVirtual":"0","kdStatusBed":"2","statusEnabled":"1"},{"id":99,"kdProfile":"0","kdKamar":"23","nomorBed":"1","isVirtual":"0","kdStatusBed":"2","statusEnabled":"1"},{"id":100,"kdProfile":"0","kdKamar":"24","nomorBed":"1","isVirtual":"0","kdStatusBed":"2","statusEnabled":"1"},{"id":101,"kdProfile":"0","kdKamar":"25","nomorBed":"1","isVirtual":"0","kdStatusBed":"2","statusEnabled":"1"},{"id":102,"kdProfile":"0","kdKamar":"26","nomorBed":"1","isVirtual":"0","kdStatusBed":"2","statusEnabled":"1"},{"id":103,"kdProfile":"0","kdKamar":"26","nomorBed":"2","isVirtual":"0","kdStatusBed":"2","statusEnabled":"1"},{"id":104,"kdProfile":"0","kdKamar":"27","nomorBed":"1","isVirtual":"0","kdStatusBed":"2","statusEnabled":"1"},{"id":105,"kdProfile":"0","kdKamar":"27","nomorBed":"2","isVirtual":"0","kdStatusBed":"2","statusEnabled":"1"},{"id":106,"kdProfile":"0","kdKamar":"28","nomorBed":"1","isVirtual":"0","kdStatusBed":"2","statusEnabled":"1"},{"id":107,"kdProfile":"0","kdKamar":"28","nomorBed":"2","isVirtual":"0","kdStatusBed":"2","statusEnabled":"1"},{"id":108,"kdProfile":"0","kdKamar":"29","nomorBed":"1","isVirtual":"0","kdStatusBed":"2","statusEnabled":"1"},{"id":109,"kdProfile":"0","kdKamar":"29","nomorBed":"2","isVirtual":"0","kdStatusBed":"2","statusEnabled":"1"},{"id":110,"kdProfile":"0","kdKamar":"30","nomorBed":"1","isVirtual":"0","kdStatusBed":"2","statusEnabled":"1"},{"id":111,"kdProfile":"0","kdKamar":"30","nomorBed":"2","isVirtual":"0","kdStatusBed":"2","statusEnabled":"1"},{"id":112,"kdProfile":"0","kdKamar":"31","nomorBed":"1","isVirtual":"0","kdStatusBed":"2","statusEnabled":"1"},{"id":113,"kdProfile":"0","kdKamar":"31","nomorBed":"2","isVirtual":"0","kdStatusBed":"2","statusEnabled":"1"},{"id":114,"kdProfile":"0","kdKamar":"32","nomorBed":"1","isVirtual":"0","kdStatusBed":"2","statusEnabled":"1"},{"id":115,"kdProfile":"0","kdKamar":"32","nomorBed":"2","isVirtual":"0","kdStatusBed":"2","statusEnabled":"1"},{"id":116,"kdProfile":"0","kdKamar":"33","nomorBed":"1","isVirtual":"0","kdStatusBed":"2","statusEnabled":"1"},{"id":117,"kdProfile":"0","kdKamar":"33","nomorBed":"2","isVirtual":"0","kdStatusBed":"2","statusEnabled":"1"},{"id":118,"kdProfile":"0","kdKamar":"34","nomorBed":"1","isVirtual":"0","kdStatusBed":"2","statusEnabled":"1"},{"id":119,"kdProfile":"0","kdKamar":"34","nomorBed":"2","isVirtual":"0","kdStatusBed":"2","statusEnabled":"1"},{"id":120,"kdProfile":"0","kdKamar":"35","nomorBed":"1","isVirtual":"0","kdStatusBed":"2","statusEnabled":"1"},{"id":121,"kdProfile":"0","kdKamar":"35","nomorBed":"2","isVirtual":"0","kdStatusBed":"2","statusEnabled":"1"},{"id":122,"kdProfile":"0","kdKamar":"36","nomorBed":"1","isVirtual":"0","kdStatusBed":"2","statusEnabled":"1"},{"id":123,"kdProfile":"0","kdKamar":"36","nomorBed":"2","isVirtual":"0","kdStatusBed":"2","statusEnabled":"1"},{"id":124,"kdProfile":"0","kdKamar":"37","nomorBed":"1","isVirtual":"0","kdStatusBed":"2","statusEnabled":"1"},{"id":125,"kdProfile":"0","kdKamar":"37","nomorBed":"2","isVirtual":"0","kdStatusBed":"2","statusEnabled":"1"}]